irma_shared-3.4.0-py3.5-nspkg.pth
irma/shared/__init__.py
irma/shared/csts.py
irma/shared/utils.py
irma/shared/schemas/__init__.py
irma/shared/schemas/artifact.py
irma/shared/schemas/file.py
irma/shared/schemas/fileext.py
irma/shared/schemas/helpers.py
irma/shared/schemas/notification.py
irma/shared/schemas/probe.py
irma/shared/schemas/proberesult.py
irma/shared/schemas/scan.py
irma/shared/schemas/srcode.py
irma/shared/schemas/tag.py
irma/shared/schemas/user.py
irma/shared/schemas/v2.py
irma/shared/schemas/v3.py
irma_shared-3.4.0.dist-info/LICENSE
irma_shared-3.4.0.dist-info/METADATA
irma_shared-3.4.0.dist-info/WHEEL
irma_shared-3.4.0.dist-info/namespace_packages.txt
irma_shared-3.4.0.dist-info/top_level.txt
irma_shared-3.4.0.dist-info/RECORD
