Metadata-Version: 2.1
Name: irma-shared
Version: 3.4.0
Summary: Objects and well-known values used by the IRMA software
Home-page: UNKNOWN
Author: irma-dev
Author-email: irma-dev@quarkslab.com
License: UNKNOWN
Platform: UNKNOWN
Requires-Dist: marshmallow (==3.3.0)
Requires-Dist: marshmallow-enum (==1.5.1)
